satori_runner-0.1.2.dist-info/METADATA
satori_runner-0.1.2.dist-info/WHEEL
satori_runner-0.1.2.dist-info/entry_points.txt
satori_runner.py
satori_runner-0.1.2.dist-info/RECORD
