Metadata-Version: 2.1
Name: satori-runner
Version: 0.1.2
Summary: Satori runner
Author-Email: Satori CI <info@satori.ci>
License: MIT
Requires-Python: >=3.9
